{
  "_description": "2026世界杯裁判数据库 v7 — 新增肢体对抗容忍度/红牌崩盘模式/关键出牌倾向",
  "_updated": "2026-06-19 北京",
  "_changes_v7": [
    "新增 physical_tolerance 字段: 裁判对激烈身体对抗的容忍程度(1-10)",
    "新增 collapse_risk 字段: 裁判出红牌导致比赛崩盘的历史倾向评估",
    "新增 card_timing_pattern 字段: 关键时刻(上半场/下半场/补时)出牌倾向",
    "新增 var_style 字段: VAR互动风格(主动介入/被动确认/不愿推翻)",
    "新增 match_impact_examples 字段: 该裁判吹罚比赛中红牌改变结果的案例",
    "细化所有裁判的2025-26赛季最新数据",
    "新增FIFA 2026新规影响评估"
  ],

  "FIFA_2026_裁判新规": {
    "_source": "新华社/ESPN/直播吧 2026年6月",
    "核心框架": "0-10分颜色量表: 0白→浅黄→深黄→橙色(可讨论区)→9分以上浅红→深红(必须出红)",
    "关键原则": "世界杯尺度比欧足联/各国联赛更宽松！只有犯规严重度达9-10分才出红牌",
    "尺度定位": "科里纳(FIFA裁判主席)主导下, 2018/2022两届仅各4红, 整体偏向宽松",
    "2026新规重点": [
      "VAR权限扩大: 可介入纠正第二张黄牌错误/认错人/错判角球",
      "严打拖延时间: 门球/界外球须5秒内发出, 超时→角球或交换球权",
      "伤病规则: 导致比赛中断的球员须离场至少1分钟",
      "赛场纪律: 争执中捂嘴/对判罚不满擅自离场→红牌",
      "定位球阻挡犯规严打, 相关进球取消"
    ],
    "已执行案例": [
      "葡萄牙vs刚果: 门将拖延开球, 被判给对手角球",
      "美国vs巴拉圭: VAR首次介入纠正黄牌错误, 改判假摔"
    ],
    "潜在矛盾": "揭幕战3红(墨西哥vs南非)与整体宽松取向的反差——可能是对赛场纪律的震慑信号"
  },

  "Abdulrahman Al-Jassim": {
    "国籍": "卡塔尔",
    "年龄": 40,
    "FIFA国际级自": 2013,
    "生涯场次": 99,
    "黄牌": 369,
    "场均黄牌_生涯": 3.7,
    "场均黄牌_2025_26": 5.2,
    "直红_生涯": 12,
    "两黄变红": 10,
    "红牌率_2025_26_QSL": "50% (7红/14场)",
    "点球率_2025_26": "64% (9点/14场)",
    "风格": "严苛出牌型(近年升级为高压型)",
    "尺度": "紧 → 近年更紧",
    "physical_tolerance": 2,
    "_physical_tolerance_note": "极低(1-10分, 越低越不容忍身体对抗)。2025-26赛季5.2黄/场, 0.5红/场, 几乎不给宽容期",
    "collapse_risk": "极高",
    "_collapse_risk_note": "最近5场平均0.8红/场(!), 任何激烈身体对抗都可能触发红牌, 对防守型弱队极为危险",
    "card_timing_pattern": "上半场即开始出牌警告(非传统'先松后紧'), 下半场70'+红牌概率显著上升",
    "var_style": "主动使用VAR, 不犹豫回看",
    "match_impact_examples": [
      "2025亚冠精英决赛: 阿赫利vs川崎前锋→严格出牌影响比赛格局",
      "2022世界杯三四名决赛: 克罗地亚vs摩洛哥→出牌控制得当",
      "2022世界杯小组赛: 美国vs威尔士→平稳执法"
    ],
    "影响": "⚠️极高风险裁判！对防守粗暴/5后卫铁桶阵的弱队极度不利！尤其是下半场落后时防守动作加大极易吃红→崩盘",
    "执法比赛": "葡萄牙 vs 刚果(金) [已赛]",
    "适用于": "任何防守型弱队vs控球型强队的比赛",
    "特点": ["出牌极频繁(2025-26年均超5黄)","不犹豫给红","对防守方不友好","VAR主动回看","近年升级为'高压执法型'"],
    "对比赛进球影响": "严苛→点球概率+5%, 但红牌后少人方崩盘概率+30%, 对手进球期望大幅上升"
  },

  "Clement Turpin": {
    "国籍": "法国",
    "年龄": 44,
    "FIFA国际级自": 2010,
    "生涯场次": 520,
    "黄牌": 1763,
    "场均黄牌": 3.4,
    "直红": 103,
    "两黄变红": 36,
    "总红": 117,
    "场均红牌": 0.27,
    "风格": "纪律严明型(中立偏严)",
    "尺度": "中等偏紧",
    "physical_tolerance": 5,
    "_physical_tolerance_note": "中等(容忍正常身体对抗, 但对过度犯规/抗议零容忍)。不是'卡牌狂人'但控制欲强",
    "collapse_risk": "中低",
    "_collapse_risk_note": "红牌率不算高(0.27/场), 但对抗议/教练不满的出牌倾向高→教练被罚下可能间接导致球队崩盘",
    "card_timing_pattern": "可上半场出多黄(如拜仁vs曼城上半场5黄), 建立早期控制, 不遵循'先松后紧'",
    "var_style": "VAR互动良好, 欧冠决赛级VAR经验",
    "match_impact_examples": [
      "2023欧冠: 拜仁vs曼城→上半场5黄+直红Upamecano(VAR后推翻), 图赫尔抗议被罚上看台→称Turpin'1/10分Grade E'",
      "2022欧冠决赛: 皇马vs利物浦→平稳执法",
      "2021欧联决赛: 比利亚雷亚尔vs曼联→纪律控制好",
      "2024欧洲杯: 英格兰0-0斯洛文尼亚→平稳"
    ],
    "特殊恩怨": "图赫尔(英格兰主帅)曾骂他'1/10分'！贝林厄姆被Turpin推过(欧冠半决赛罚点时)",
    "影响": "对英格兰球员的特殊心理压力→贝林厄姆/凯恩与Turpin有过节。Turpin对教练抗议零容忍→图赫尔可能再次被罚",
    "执法比赛": "英格兰 vs 克罗地亚 [已赛]",
    "特点": ["欧足联顶级裁判(欧冠+欧联决赛)","VAR互动良好","对教练抗议零容忍","曾被图赫尔评Grade E","上半场就建立控制"],
    "对比赛进球影响": "中等偏严→正常比赛进球期望, 但点球判罚率高(7点/最近31场)"
  },

  "Gustavo Tejera": {
    "国籍": "乌拉圭",
    "年龄": 38,
    "FIFA国际级自": 2018,
    "生涯场次": 344,
    "黄牌": 1733,
    "场均黄牌_生涯": 5.04,
    "直红_生涯": 44,
    "两黄变红": 18,
    "总红_生涯": 62,
    "场均红牌": 0.18,
    "红牌概率": "约三分之一比赛出红",
    "风格": "南美高压出牌型",
    "尺度": "紧 → 极紧",
    "physical_tolerance": 2,
    "_physical_tolerance_note": "极低(1-10分)！场均5黄！对重复犯规零容忍！南美裁判中对身体对抗最不容忍之一",
    "collapse_risk": "极高",
    "_collapse_risk_note": "每三场出一红！世界杯前最后两场俱乐部比赛出12黄→状态'火热'。防守粗暴型球队面对他极可能主力吃红→少人崩盘",
    "card_timing_pattern": "上半场出牌频繁(建立控制), 下半场60-75'有'红牌窗口期'(疲劳导致犯规动作变大→触发第二黄/直红)",
    "var_style": "南美VAR风格→倾向维护场上权威, VAR介入相对保守",
    "match_impact_examples": [
      "2026世界杯: 墨西哥vs韩国→全场韩国0射正+韩国球员多次吃牌后进攻缩手缩脚→验证了严格裁判对防守方的巨大影响",
      "2025-26赛季最后两场俱乐部比赛: 共12黄→'火热'出牌状态延续到世界杯"
    ],
    "争议": "墨西哥vs韩国: 全裁判组南美人/西班牙语→韩国赛前抗议'同语言背景', 韩国0-1失利后部分媒体称'争议'",
    "影响": "⚠️极高风险裁判！对防守粗暴/身体对抗型球队极度不利！5黄/场的出牌频率意味着防守方核心大概率染黄→下半场缩手缩脚或吃红→崩盘",
    "执法比赛": "墨西哥 vs 韩国 [已赛]",
    "特点": ["场均5黄!几乎不给宽容","对重复犯规零容忍","FIFA 2018年起国际级","南美裁判风格→对东道主可能偏宽松","每三场出一红"],
    "对比赛进球影响": "严苛裁判→防守方缩手缩脚, 进攻方获得更多空间→总进球期望略微上升, 强弱队差距被放大"
  },

  "João Pinheiro": {
    "国籍": "葡萄牙",
    "年龄": 38,
    "生涯场次": 280,
    "黄牌": 1120,
    "场均黄牌": 4.0,
    "直红": 18,
    "风格": "欧足联精英级技术流保护型",
    "尺度": "偏严(对技术流有利)",
    "physical_tolerance": 4,
    "_physical_tolerance_note": "中低。保护技术流球员, 对过度身体对抗出牌快, 但非'高压型'",
    "collapse_risk": "中",
    "_collapse_risk_note": "红牌率中等, 但对防守动作大的弱队不利→可能积累黄牌导致下半场受限",
    "card_timing_pattern": "上半场警告性出牌→中场后升级→75'后对疲劳犯规出牌增多",
    "var_style": "VAR互动良好, 欧足联精英培训",
    "match_impact_examples": [
      "2026世界杯: 瑞士vs波黑→对技术流瑞士有利, 波黑身体对抗受限→红牌后波黑崩盘"
    ],
    "影响": "对技术传控流球队有利！身体对抗型弱队需注意吃牌",
    "执法比赛": "瑞士 vs 波黑 [已赛]",
    "特点": ["欧足联精英裁判","VAR互动良好","对技术流有利","限制过度身体对抗"],
    "对比赛进球影响": "保护技术流→传控型球队控球率+5-8%, 进攻更流畅→总进球期望微升"
  },

  "Anthony Taylor": {
    "国籍": "英格兰",
    "年龄": 47,
    "生涯场次": 450,
    "风格": "英超经验丰富型",
    "尺度": "中等偏松",
    "physical_tolerance": 7,
    "_physical_tolerance_note": "较高。英超传统宽松风格→允许更多身体接触和对抗, 不轻易吹停比赛",
    "collapse_risk": "低",
    "_collapse_risk_note": "宽松风格下红牌概率低, 比赛节奏流畅, 不容易因出牌导致崩盘",
    "card_timing_pattern": "传统英超风格→上半场宽容, 下半场仅对明显犯规出牌",
    "var_style": "VAR: Ivan Bebek(克罗地亚), 助理VAR: Jarred Gillett(澳大利亚)",
    "match_impact_examples": [
      "2022世界杯: 执法2场",
      "2026世界杯: 乌兹别克vs哥伦比亚→宽松尺度对防守型乌兹别克有利(身体对抗不被频繁吹停)"
    ],
    "影响": "对防守/身体对抗型弱队相对有利",
    "执法比赛": "乌兹别克斯坦 vs 哥伦比亚 [已赛]",
    "特点": ["FIFA 2013年起国际级","2022世界杯执法2场","英超老牌裁判","宽松尺度"],
    "对比赛进球影响": "宽松→身体对抗多→比赛节奏快→总进球期望微升, 胜负更多取决于实力而非裁判"
  },

  "Glenn Nyberg": {
    "国籍": "瑞典",
    "年龄": 37,
    "风格": "北欧简洁型",
    "尺度": "中等",
    "physical_tolerance": 6,
    "_physical_tolerance_note": "中高。北欧裁判传统较宽容, 不过度干预比赛",
    "collapse_risk": "低",
    "_collapse_risk_note": "中等偏宽松→红牌风险低",
    "card_timing_pattern": "均衡出牌",
    "var_style": "欧足联新锐, 奥运会VAR经验",
    "match_impact_examples": [],
    "影响": "身体对抗较多的比赛不会频繁吹停",
    "执法比赛": "加纳 vs 巴拿马 [已赛]",
    "特点": ["欧足联新锐裁判","奥运会经验","瑞典裁判传统较宽容"],
    "对比赛进球影响": "正常→比赛流畅度好"
  },

  "Cristian Garay": {
    "国籍": "智利",
    "年龄": 37,
    "生涯场次": 180,
    "场均黄牌": 3.8,
    "直红": 12,
    "风格": "南美裁判风格",
    "尺度": "中等",
    "physical_tolerance": 5,
    "_physical_tolerance_note": "中等。南美裁判风格下正常尺度",
    "collapse_risk": "中低",
    "_collapse_risk_note": "红牌率中等",
    "card_timing_pattern": "南美风格→偶尔对激烈对抗容忍较高",
    "var_style": "南美VAR经验",
    "match_impact_examples": [
      "2026世界杯: 加拿大vs卡塔尔→加拿大6-0屠杀(加拿大东道主因素+卡塔尔2红)"
    ],
    "影响": "东道主(加拿大)因素需考虑, 对非美洲球队可能偏严",
    "执法比赛": "加拿大 vs 卡塔尔 [已赛]",
    "特点": ["FIFA 2021年起国际级","南美预选赛经验","对东道主可能偏宽松"],
    "对比赛进球影响": "适中"
  },

  "尺度总结": {
    "最严_出牌狂人": [
      "Gustavo Tejera (乌拉圭) — 场均5黄!44+直红!每三场一红!",
      "Abdulrahman Al-Jassim (卡塔尔) — 2025-26季0.5红/场!最近5场平均0.8红!"
    ],
    "次严_纪律控制型": [
      "João Pinheiro (葡萄牙) — 场均4黄, 保护技术流",
      "Clement Turpin (法国) — 场均3.4黄, 对教练抗议零容忍"
    ],
    "中等型": [
      "Glenn Nyberg (瑞典) — 北欧宽容传统",
      "Cristian Garay (智利) — 南美正常尺度"
    ],
    "偏松型": [
      "Anthony Taylor (英格兰) — 英超宽松风格, 身体对抗不会被频繁吹停"
    ]
  },

  "裁判→崩盘风险评估": {
    "_description": "综合裁判出牌倾向+球队防守风格→预测红牌导致少人崩盘的概率",
    "极高风险组合": "严苛裁判(Tejera/Al-Jassim) + 防守粗暴型弱队(如刚果5后卫铁桶/韩国身体对抗型) → 崩盘概率+30%",
    "高风险组合": "严苛裁判 + 任何防守型球队 → 至少1人染黄→下半场缩手缩脚",
    "中等风险": "纪律型裁判(Turpin/Pinheiro) + 身体对抗型球队",
    "低风险": "宽松型裁判(Taylor/Nyberg) → 比赛主要由实力决定",
    "已验证案例": [
      "Tejera执法墨西哥vs韩国→韩国全场0射正(缩手缩脚)",
      "Pinheiro执法瑞士vs波黑→波黑80'红牌→连丢3球崩盘",
      "Al-Jassim执法葡萄牙vs刚果→刚果5后卫铁桶需格外小心(结果1-1平→刚果策略成功)"
    ]
  },

  "裁判对南美/中北美球队的潜在偏袒": {
    "_description": "基于语言/文化/地理因素分析",
    "南美裁判(Tejera/Garay)": "对南美/西语球队可能略偏宽松, 对欧洲/亚洲球队可能偏严",
    "欧洲裁判(Turpin/Pinheiro/Taylor/Nyberg)": "对欧洲球队无偏袒, 技术流球队受益",
    "亚洲裁判(Al-Jassim)": "对亚洲球队无特殊偏袒, 纯按规则执法",
    "已出现争议": "韩国vs墨西哥(全南美裁判组)→韩国赛前抗议, 赛后部分媒体称'争议'"
  }
}
